Waiter.py
Swaiter-1.0.4.dist-info/LICENSE
Swaiter-1.0.4.dist-info/METADATA
Swaiter-1.0.4.dist-info/WHEEL
Swaiter-1.0.4.dist-info/top_level.txt
Swaiter-1.0.4.dist-info/RECORD
