Metadata-Version: 2.1
Name: Swaiter
Version: 1.0.4
Summary: The loop waits until the selenium element has loaded.
Author-email: Beier <1601684622@qq.com>
Project-URL: github, https://github.com/srx-2000/Swaiter
Keywords: selenium,crawler
Requires-Python: >=3.7
License-File: LICENSE
Requires-Dist: selenium (>=4.9.0)
Requires-Dist: loguru (>=0.7.0)
